Workbook

Sheet Orçamento_Março
A1: ORÇAMENTO DOMÉSTICO/JANEIRO
B2: RENDA FAMILIAR | C2: 2400
B3: GASTOS TOTAIS | C3: =SUM(C17+E17+G17+I17+K17+M17+O17+Q17) -> 1764.5
B4: SALDO DO MÊS | C4: =C2-C3 -> 635.5
A6: Moradia | D6: Saúde | F6: Alimentação | H6: Transporte | J6: Vestuário | L6: Educação | N6: Lazer | P6: Investimentos
A7: Custos | D7: Custos | F7: Custos | H7: Custos | J7: Custos | L7: Custos | N7: Custos | P7: Custos
A8: 1 | B8: Aluguel | D8: Remédios | F8: Supermercado | H8: Transporte público | I8: 50 | J8: Roupas | L8: Mensalidade/Universidade | M8: 381 | N8: Passeios | P8: CDI | Q8: 200
A9: 2 | B9: Condomínio | D9: Plano de saúde | E9: 85 | F9: Feira | H9: Carro/Combustível | J9: Calçados | L9: Kumon/Inglês | M9: 315 | N9: Viagens | P9: Tesouro Direto | Q9: 80
A10: 3 | B10: Celular | D10: Consulta médica | F10: Açougue | H10: IPVA | N10: Mouse 4/6 | O10: 119.8
A11: 4 | B11: Luz | D11: Exame | F11: Almoço | G11: 53.75 | H11: Prova da Habilitação | I11: 200
A12: 5 | B12: Gás | D12: Dentista
A13: 6 | B13: Água/esgoto | D13: Produtos de Higiene Pessoal
A14: 7 | B14: Internet | D14: INSS | E14: 179.95
A15: 8 | B15: Serviços de Streaming | D15: Academia | E15: 100
A16: 9 | B16: IPTU
B17: SUBTOTAL | D17: SUBTOTAL | E17: =SUM(E9:E16) -> 364.95 | F17: SUBTOTAL | G17: =SUM(G8:G16) -> 53.75 | H17: SUBTOTAL | I17: =SUM(I8:I16) -> 250 | J17: SUBTOTAL | K17: =SUM(K8:K16) -> 0 | L17: SUBTOTAL | M17: =SUM(M8:M16) -> 696 | N17: SUBTOTAL | O17: =SUM(O9:O16) -> 119.8 | P17: SUBTOTAL | Q17: =SUM(Q8:Q16) -> 280
B21: GASTOS TOTAIS | C21: CUSTO
B22: Moradia | C22: =C17 -> 0
B23: Saúde | C23: =E17 -> 364.95
B24: Alimentação | C24: =G17 -> 53.75
B25: Transporte | C25: =I17 -> 250
B26: Vestuário | C26: =K17 -> 0
B27: Educação | C27: =M17 -> 696
B28: Lazer | C28: =O17 -> 119.8
B29: Investimentos | C29: =Q17 -> 280

Sheet Orçamento_Abril
A1: ORÇAMENTO DOMÉSTICO/JANEIRO
B2: RENDA FAMILIAR | C2: 2400
B3: GASTOS TOTAIS | C3: =SUM(C17+E17+G17+I17+M17+O17+Q17) -> 1323.7
B4: SALDO DO MÊS | C4: =C2-C3 -> 1076.3
A6: Moradia | D6: Saúde | F6: Alimentação | H6: Transporte | J6: Vestuário | L6: Educação | N6: Lazer | P6: Investimentos
A7: Custos | D7: Custos | F7: Custos | H7: Custos | J7: Custos | L7: Custos | N7: Custos | P7: Custos
A8: 1 | B8: Aluguel | C8: 0 | D8: Remédios | F8: Supermercado | H8: Transporte público | I8: 50 | J8: Roupas | L8: Mensalidade/Universidade | M8: 300 | N8: Passeios | P8: CDI | Q8: 200
A9: 2 | B9: Condomínio | C9: 0 | D9: Plano de saúde | E9: 85 | F9: Feira | H9: Carro/Combustível | J9: Calçados | L9: Material Escolar | N9: Viagens | P9: Tesouro Direto | Q9: 40
A10: 3 | B10: Celular | C10: 0 | D10: Consulta médica | F10: Açougue | H10: IPVA | L10: Kumon/Inglês | M10: 315
A11: 4 | B11: Luz | C11: 0 | D11: Exame | F11: Almoço | G11: 53.75
A12: 5 | B12: Gás | C12: 0 | D12: Dentista
A13: 6 | B13: Água/esgoto | C13: 0 | D13: Produtos de Higiene Pessoal
A14: 7 | B14: Internet | C14: 0 | D14: INSS | E14: 179.95
A15: 8 | B15: Serviços de Streaming | C15: 0 | D15: Academia | E15: 100
A16: 9 | B16: IPTU | C16: 0
B17: SUBTOTAL | C17: =SUM(C8:C16) -> 0 | D17: SUBTOTAL | E17: =SUM(E9:E16) -> 364.95 | F17: SUBTOTAL | G17: =SUM(G8:G16) -> 53.75 | H17: SUBTOTAL | I17: =SUM(I8:I16) -> 50 | J17: SUBTOTAL | L17: SUBTOTAL | M17: =SUM(M8:M16) -> 615 | N17: SUBTOTAL | O17: =SUM(O9:O16) -> 0 | P17: SUBTOTAL | Q17: =SUM(Q8:Q16) -> 240

Sheet Total Geral_Trimestral
A1: Categoria | B1: Março | C1: Abril | D1: Maio | E1: TOTAL GERAL | F1: MÉDIA GERAL
A2: Alimentação | B2: =Orçamento_Março!G17 -> 53.75 | E2: =SUM(B2:D2) -> 53.75 | F2: =AVERAGE(B2:D2) -> 53.75
A3: Educação | B3: =Orçamento_Março!M17 -> 696 | E3: =SUM(B3:D3) -> 696 | F3: =AVERAGE(B3:D3) -> 696
A4: Investimentos | B4: =Orçamento_Março!Q17 -> 280 | E4: =SUM(B4:D4) -> 280 | F4: =AVERAGE(B4:D4) -> 280
A5: Lazer | B5: =Orçamento_Março!O17 -> 119.8 | E5: =SUM(B5:D5) -> 119.8 | F5: =AVERAGE(B5:D5) -> 119.8
A6: Moradia | B6: =Orçamento_Março!C17 -> 0 | C6: =Orçamento_Abril!C17 -> 0 | E6: =SUM(B6:D6) -> 0 | F6: =AVERAGE(B6:D6) -> 0
A7: Saúde | B7: =Orçamento_Março!E17 -> 364.95 | C7: =Orçamento_Abril!E17 -> 364.95 | E7: =SUM(B7:D7) -> 729.9 | F7: =AVERAGE(B7:D7) -> 364.95
A8: Transporte | B8: =Orçamento_Março!I17 -> 250 | E8: =SUM(B8:D8) -> 250 | F8: =AVERAGE(B8:D8) -> 250
A9: Vestuário | B9: =Orçamento_Março!K17 -> 0 | E9: =SUM(B9:D9) -> 0 | F9: =AVERAGE(B9:D9) -> 0
A10: TOTAL GERAL | B10: =SUM(B2:B9) -> 1764.5 | C10: =SUM(C2:C9) -> 364.95 | E10: =SUM(B10:C10:D10) -> 2129.45 | F10: =SUM(F2:F9) -> 1764.5
F11: =MAX(F2:F9) -> 696
F12: =MIN(F2:F9) -> 0
